[
  {
    "datum": "2.1",
    "uhrzeit": "Gerhard Wolfert",
    "spielort": "12",
    "heim": "2:10",
    "gast": "5:7",
    "ergebnis": null,
    "status": "geplant"
  },
  {
    "datum": "2.2",
    "uhrzeit": "Christian Heer",
    "spielort": "13",
    "heim": "3:10",
    "gast": "4:8",
    "ergebnis": null,
    "status": "geplant"
  },
  {
    "datum": "2.3",
    "uhrzeit": "Erik Stiefel",
    "spielort": "10",
    "heim": "0:2",
    "gast": "1:1",
    "ergebnis": "5:3",
    "status": "gespielt"
  },
  {
    "datum": "2.4",
    "uhrzeit": "Günter Friedel",
    "spielort": "14",
    "heim": "0:1",
    "gast": "",
    "ergebnis": "6:4",
    "status": "gespielt"
  },
  {
    "datum": "2.5",
    "uhrzeit": "Paul Stumpp",
    "spielort": "0",
    "heim": "",
    "gast": "",
    "ergebnis": null,
    "status": "geplant"
  },
  {
    "datum": "2.6",
    "uhrzeit": "Florian Wolfert",
    "spielort": "9",
    "heim": "",
    "gast": "",
    "ergebnis": "3:1",
    "status": "gespielt"
  },
  {
    "datum": "2.7",
    "uhrzeit": "Johannes Scherrer",
    "spielort": "4",
    "heim": "",
    "gast": "",
    "ergebnis": "0:1",
    "status": "gespielt"
  },
  {
    "datum": "3.1",
    "uhrzeit": "Melanie Wolfert",
    "spielort": "12",
    "heim": "",
    "gast": "",
    "ergebnis": null,
    "status": "geplant"
  },
  {
    "datum": "3.2",
    "uhrzeit": "Stefan Wolfert",
    "spielort": "2",
    "heim": "",
    "gast": "",
    "ergebnis": null,
    "status": "geplant"
  },
  {
    "datum": "3.3",
    "uhrzeit": "Martin Schneider",
    "spielort": "2",
    "heim": "",
    "gast": "",
    "ergebnis": "0:1",
    "status": "gespielt"
  },
  {
    "datum": "3.6",
    "uhrzeit": "Dominik Huber",
    "spielort": "3",
    "heim": "",
    "gast": "",
    "ergebnis": null,
    "status": "geplant"
  },
  {
    "datum": "3.7",
    "uhrzeit": "Frank Repovs",
    "spielort": "1",
    "heim": "",
    "gast": "",
    "ergebnis": null,
    "status": "geplant"
  },
  {
    "datum": "3.9",
    "uhrzeit": "Adrian Bach",
    "spielort": "1",
    "heim": "",
    "gast": "",
    "ergebnis": null,
    "status": "geplant"
  },
  {
    "datum": "3.13",
    "uhrzeit": "Dietrich Kruth",
    "spielort": "1",
    "heim": "",
    "gast": "",
    "ergebnis": null,
    "status": "geplant"
  }
]