[
  {
    "rang": "1",
    "mannschaft": "TTF Laudenbach V",
    "partien": "0",
    "siege": "0",
    "unentschieden": "0",
    "niederlagen": "0",
    "spiele": "0:0",
    "spieleDifferenz": "0",
    "punkte": "0:0"
  },
  {
    "rang": "2",
    "mannschaft": "TSV Markelsheim II",
    "partien": "0",
    "siege": "0",
    "unentschieden": "0",
    "niederlagen": "0",
    "spiele": "0:0",
    "spieleDifferenz": "0",
    "punkte": "0:0"
  },
  {
    "rang": "3",
    "mannschaft": "VFB Bad Mergentheim IV",
    "partien": "0",
    "siege": "0",
    "unentschieden": "0",
    "niederlagen": "0",
    "spiele": "0:0",
    "spieleDifferenz": "0",
    "punkte": "0:0"
  },
  {
    "rang": "4",
    "mannschaft": "SV Elpersheim IV",
    "partien": "0",
    "siege": "0",
    "unentschieden": "0",
    "niederlagen": "0",
    "spiele": "0:0",
    "spieleDifferenz": "0",
    "punkte": "0:0"
  },
  {
    "rang": "5",
    "mannschaft": "FC Creglingen II",
    "partien": "0",
    "siege": "0",
    "unentschieden": "0",
    "niederlagen": "0",
    "spiele": "0:0",
    "spieleDifferenz": "0",
    "punkte": "0:0"
  },
  {
    "rang": "6",
    "mannschaft": "SC Buchenbach V",
    "partien": "0",
    "siege": "0",
    "unentschieden": "0",
    "niederlagen": "0",
    "spiele": "0:0",
    "spieleDifferenz": "0",
    "punkte": "0:0"
  },
  {
    "rang": "7",
    "mannschaft": "TSV Dörzbach II",
    "partien": "0",
    "siege": "0",
    "unentschieden": "0",
    "niederlagen": "0",
    "spiele": "0:0",
    "spieleDifferenz": "0",
    "punkte": "0:0"
  }
]